{
  "schema_version": "1.1",
  "type_definitions": [
    {
      "type": "account",
      "relations": {},
      "metadata": {
        "relations": {}
      }
    },
    {
      "type": "tenant",
      "relations": {
        "member": {
          "this": {}
        },
        "admin": {
          "this": {}
        },
        "security_admin": {
          "this": {}
        }
      },
      "metadata": {
        "relations": {
          "member": {
            "directly_related_user_types": [
              {
                "type": "account"
              }
            ]
          },
          "admin": {
            "directly_related_user_types": [
              {
                "type": "account"
              }
            ]
          },
          "security_admin": {
            "directly_related_user_types": [
              {
                "type": "account"
              }
            ]
          }
        }
      }
    },
    {
      "type": "org_unit",
      "relations": {
        "tenant": {
          "this": {}
        },
        "parent": {
          "this": {}
        },
        "member": {
          "this": {}
        },
        "manager": {
          "this": {}
        },
        "member_recursive": {
          "union": {
            "child": [
              {
                "computedUserset": {
                  "relation": "member"
                }
              },
              {
                "tupleToUserset": {
                  "tupleset": {
                    "relation": "parent"
                  },
                  "computedUserset": {
                    "relation": "member_recursive"
                  }
                }
              }
            ]
          }
        },
        "viewer": {
          "union": {
            "child": [
              {
                "computedUserset": {
                  "relation": "member"
                }
              },
              {
                "computedUserset": {
                  "relation": "manager"
                }
              },
              {
                "tupleToUserset": {
                  "tupleset": {
                    "relation": "parent"
                  },
                  "computedUserset": {
                    "relation": "viewer"
                  }
                }
              },
              {
                "tupleToUserset": {
                  "tupleset": {
                    "relation": "tenant"
                  },
                  "computedUserset": {
                    "relation": "admin"
                  }
                }
              }
            ]
          }
        },
        "editor": {
          "union": {
            "child": [
              {
                "computedUserset": {
                  "relation": "manager"
                }
              },
              {
                "tupleToUserset": {
                  "tupleset": {
                    "relation": "tenant"
                  },
                  "computedUserset": {
                    "relation": "admin"
                  }
                }
              }
            ]
          }
        }
      },
      "metadata": {
        "relations": {
          "tenant": {
            "directly_related_user_types": [
              {
                "type": "tenant"
              }
            ]
          },
          "parent": {
            "directly_related_user_types": [
              {
                "type": "org_unit"
              }
            ]
          },
          "member": {
            "directly_related_user_types": [
              {
                "type": "account"
              }
            ]
          },
          "manager": {
            "directly_related_user_types": [
              {
                "type": "account"
              }
            ]
          }
        }
      }
    },
    {
      "type": "user_group",
      "relations": {
        "member": {
          "this": {}
        },
        "manager": {
          "this": {}
        }
      },
      "metadata": {
        "relations": {
          "member": {
            "directly_related_user_types": [
              {
                "type": "account"
              }
            ]
          },
          "manager": {
            "directly_related_user_types": [
              {
                "type": "account"
              }
            ]
          }
        }
      }
    },
    {
      "type": "assumable_role",
      "relations": {
        "tenant": {
          "this": {}
        },
        "trusted_user": {
          "this": {}
        },
        "trusted_group": {
          "this": {}
        },
        "approver": {
          "this": {}
        },
        "can_assume": {
          "union": {
            "child": [
              {
                "computedUserset": {
                  "relation": "trusted_user"
                }
              },
              {
                "computedUserset": {
                  "relation": "trusted_group"
                }
              },
              {
                "tupleToUserset": {
                  "tupleset": {
                    "relation": "tenant"
                  },
                  "computedUserset": {
                    "relation": "admin"
                  }
                }
              }
            ]
          }
        },
        "can_approve": {
          "union": {
            "child": [
              {
                "computedUserset": {
                  "relation": "approver"
                }
              },
              {
                "tupleToUserset": {
                  "tupleset": {
                    "relation": "tenant"
                  },
                  "computedUserset": {
                    "relation": "security_admin"
                  }
                }
              }
            ]
          }
        }
      },
      "metadata": {
        "relations": {
          "tenant": {
            "directly_related_user_types": [
              {
                "type": "tenant"
              }
            ]
          },
          "trusted_user": {
            "directly_related_user_types": [
              {
                "type": "account"
              }
            ]
          },
          "trusted_group": {
            "directly_related_user_types": [
              {
                "type": "user_group",
                "relation": "member"
              }
            ]
          },
          "approver": {
            "directly_related_user_types": [
              {
                "type": "account"
              }
            ]
          }
        }
      }
    },
    {
      "type": "agent_tool",
      "relations": {
        "tenant": {
          "this": {}
        },
        "runner": {
          "this": {}
        },
        "can_run": {
          "union": {
            "child": [
              {
                "computedUserset": {
                  "relation": "runner"
                }
              },
              {
                "tupleToUserset": {
                  "tupleset": {
                    "relation": "tenant"
                  },
                  "computedUserset": {
                    "relation": "admin"
                  }
                }
              }
            ]
          }
        }
      },
      "metadata": {
        "relations": {
          "tenant": {
            "directly_related_user_types": [
              {
                "type": "tenant"
              }
            ]
          },
          "runner": {
            "directly_related_user_types": [
              {
                "type": "account"
              }
            ]
          }
        }
      }
    },
    {
      "type": "hr.employee",
      "relations": {
        "owner": {
          "this": {}
        },
        "manager": {
          "this": {}
        },
        "org": {
          "this": {}
        },
        "read": {
          "union": {
            "child": [
              {
                "computedUserset": {
                  "relation": "owner"
                }
              },
              {
                "computedUserset": {
                  "relation": "manager"
                }
              },
              {
                "tupleToUserset": {
                  "tupleset": {
                    "relation": "org"
                  },
                  "computedUserset": {
                    "relation": "manager"
                  }
                }
              },
              {
                "tupleToUserset": {
                  "tupleset": {
                    "relation": "org"
                  },
                  "computedUserset": {
                    "relation": "member_recursive"
                  }
                }
              }
            ]
          }
        },
        "update": {
          "computedUserset": {
            "relation": "owner"
          }
        },
        "delete": {
          "computedUserset": {
            "relation": "owner"
          }
        },
        "invite": {
          "computedUserset": {
            "relation": "owner"
          }
        },
        "update_status": {
          "computedUserset": {
            "relation": "owner"
          }
        },
        "status_transition": {
          "computedUserset": {
            "relation": "owner"
          }
        }
      },
      "metadata": {
        "relations": {
          "owner": {
            "directly_related_user_types": [
              {
                "type": "account"
              }
            ]
          },
          "manager": {
            "directly_related_user_types": [
              {
                "type": "account"
              }
            ]
          },
          "org": {
            "directly_related_user_types": [
              {
                "type": "org_unit"
              }
            ]
          }
        }
      }
    },
    {
      "type": "agent.knowledge_article",
      "relations": {
        "viewer": {
          "this": {}
        },
        "read": {
          "computedUserset": {
            "relation": "viewer"
          }
        }
      },
      "metadata": {
        "relations": {
          "viewer": {
            "directly_related_user_types": [
              {
                "type": "account"
              }
            ]
          }
        }
      }
    }
  ]
}
